MANIFEST.in
README.rst
setup.cfg
setup.py
docs/HISTORY.txt
src/mobi/__init__.py
src/mobi.rendering.egg-info/PKG-INFO
src/mobi.rendering.egg-info/SOURCES.txt
src/mobi.rendering.egg-info/dependency_links.txt
src/mobi.rendering.egg-info/namespace_packages.txt
src/mobi.rendering.egg-info/requires.txt
src/mobi.rendering.egg-info/top_level.txt
src/mobi/rendering/__init__.py
src/mobi/rendering/configure.zcml
src/mobi/rendering/engine.py
src/mobi/rendering/expressions.py
src/mobi/rendering/resource.py
src/mobi/rendering/widgets.py
src/mobi/rendering/default_skin/layout.pt
src/mobi/rendering/default_skin/BasicAddressWidget/index.pt
src/mobi/rendering/default_skin/GoogleMapWidget/index.pt
src/mobi/rendering/default_skin/ImageURLWidget/index.pt
src/mobi/rendering/default_skin/StaticGoogleMapWidget/index.pt
src/mobi/rendering/tests/doctest_engine.py
src/mobi/rendering/tests/doctest_widgets.py
src/mobi/rendering/tests/templates/model_default_widget.pt
src/mobi/rendering/tests/templates/model_widget_standard.pt
src/mobi/rendering/tests/templates/page.pt
src/mobi/rendering/tests/templates/text_line_widget_advanced.pt
src/mobi/rendering/tests/templates/text_line_widget_default.pt