Metadata-Version: 1.0
Name: mobi.rendering
Version: 1.0
Summary: Mobile Device management
Home-page: infrae.com
Author: Infrae
Author-email: info@infrae.com
License: UNKNOWN
Platform: UNKNOWN
